serial_packet/__init__.py
serial_packet/crc.py
serial_packet/serial_packet.py
serial_packet-0.1.dist-info/LICENSE
serial_packet-0.1.dist-info/METADATA
serial_packet-0.1.dist-info/WHEEL
serial_packet-0.1.dist-info/top_level.txt
serial_packet-0.1.dist-info/RECORD
